README.md
setup.py
practicando_modulos/__init__.py
practicando_modulos/cal.py
practicando_modulos/config.py
practicando_modulos.egg-info/PKG-INFO
practicando_modulos.egg-info/SOURCES.txt
practicando_modulos.egg-info/dependency_links.txt
practicando_modulos.egg-info/top_level.txt