Metadata-Version: 2.1
Name: practicando_modulos
Version: 0.1
Summary: ejercicios con modulos
Author: Eddy Mamani Mamani
Author-email: emamanimamani630@gmail.com
License: MIT
Keywords: testing,logging,example
